craves/__init__.py
craves-0.0.1.dist-info/LICENSE
craves-0.0.1.dist-info/METADATA
craves-0.0.1.dist-info/WHEEL
craves-0.0.1.dist-info/top_level.txt
craves-0.0.1.dist-info/RECORD
