Metadata-Version: 2.1
Name: craves
Version: 0.0.1
Summary: Craves: Controlling Robotic Arm with a Vision and Economic System
Home-page: https://github.com/qiuwch/craves
Author: Craves Team
Author-email: qiuwch@gmail.com
License: UNKNOWN
Platform: UNKNOWN
Classifier: Programming Language :: Python :: 3
Classifier: License :: OSI Approved :: MIT License
Classifier: Operating System :: OS Independent
